LICENSE
README.rst
setup.py
ChemW.egg-info/PKG-INFO
ChemW.egg-info/SOURCES.txt
ChemW.egg-info/dependency_links.txt
ChemW.egg-info/requires.txt
ChemW.egg-info/top_level.txt
chemw/__init__.py
chemw/amino_acids_masses.json
chemw/mw.py
test/__init__.py
test/test_mw.py
test/databases/Amm.dat
test/databases/ColdChem.dat
test/databases/Tipping_Hurley.dat
test/databases/core10.dat
test/databases/frezchem.dat
test/databases/iso.dat
test/databases/llnl.dat
test/databases/minteq.dat
test/databases/minteq.v4.dat
test/databases/phreeqc.dat
test/databases/pitzer.dat
test/databases/sit.dat
test/databases/wateq4f.dat