Metadata-Version: 2.1
Name: ChemW
Version: 0.3.2
Summary: Calculates the Molecular Weight, to the appropriate significant digits, from a string of an arbitrary chemical formula, a protein sequence of one- or three-letter codes, or chemical common names that are recognized by PubChem.
Home-page: https://github.com/freiburgermsu/chemw
Author: Andrew Freiburger
Author-email: andrewfreiburger@gmail.com
License: MIT
Keywords: chemistry,math,mass,weight,PHREEQC,molecular,mineral,formula,calculate,significant,digits,figures,sigfigs,proteins,enzymes
Platform: UNKNOWN
License-File: LICENSE
